model_compressor_impl/VERSION.txt
model_compressor_impl/__init__.py
model_compressor_impl/api/__init__.py
model_compressor_impl/api/api.py
model_compressor_impl/api/ptq_auto_optimization.py
model_compressor_impl/api/qformat_modify.py
model_compressor_impl/calib/__init__.py
model_compressor_impl/calib/calibration.py
model_compressor_impl/calib/control_tensor_quantizer.py
model_compressor_impl/calib/types.py
model_compressor_impl/calib/utils.py
model_compressor_impl/calib/kv_sep_calibrate/__init__.py
model_compressor_impl/calib/kv_sep_calibrate/kv_sep_calibrate.py
model_compressor_impl/calib/no_split_calibrate/__init__.py
model_compressor_impl/calib/no_split_calibrate/no_split_calibrate.py
model_compressor_impl/calib/no_split_calibrate/transform_model.py
model_compressor_impl/calib/simple_calibrate/__init__.py
model_compressor_impl/calib/simple_calibrate/act_calibrate.py
model_compressor_impl/calib/simple_calibrate/model_forward.py
model_compressor_impl/calib/simple_calibrate/simple_calibrate.py
model_compressor_impl/calib/simple_calibrate/weight_calibrate.py
model_compressor_impl/calib/simple_calibrate/zp_equalize.py
model_compressor_impl/calib/split_calibrate/__init__.py
model_compressor_impl/calib/split_calibrate/split_calibrate.py
model_compressor_impl/descriptor/__init__.py
model_compressor_impl/descriptor/descriptor.py
model_compressor_impl/helper/__init__.py
model_compressor_impl/helper/share.py
model_compressor_impl/helper/dynamo/__init__.py
model_compressor_impl/helper/dynamo/dynamo_graph_wrapper.py
model_compressor_impl/helper/dynamo/example_input_capturer.py
model_compressor_impl/helper/dynamo/trace_model.py
model_compressor_impl/helper/symbolic/__init__.py
model_compressor_impl/helper/symbolic/fxgraph_causallm.py
model_compressor_impl/helper/symbolic/gptj_custom_hf_trace.py
model_compressor_impl/helper/symbolic/llama_custom_hf_trace.py
model_compressor_impl/helper/symbolic/quantcausallm.py
furiosa_model_compressor_impl-2025.3.0.dist-info/METADATA
furiosa_model_compressor_impl-2025.3.0.dist-info/WHEEL
furiosa_model_compressor_impl-2025.3.0.dist-info/RECORD
