Metadata-Version: 2.4
Name: furiosa-model-compressor-impl
Version: 2025.3.0
Author-email: "FuriosaAI Inc." <pkg@furiosa.ai>
Requires-Python: >=3.9
Requires-Dist: furiosa-llm-models~=2025.3.0
Requires-Dist: graphviz==0.20.3
Requires-Dist: parse==1.20.2
Requires-Dist: pydot==2.0.0
Requires-Dist: ruamel-yaml>=0.17.21
Requires-Dist: scipy<1.12,>=1.10.1
Requires-Dist: torch==2.5.1
Requires-Dist: torchvision==0.20.1
Requires-Dist: tqdm==4.67.1
Requires-Dist: transformers==4.48.1
Provides-Extra: nstest
Requires-Dist: pandas; extra == 'nstest'
